loco/__init__.py
loco/loco.py
loco/utils.py
tests/__init__.py
tests/all_test.py
loco-0.1.33.dist-info/LICENSE
loco-0.1.33.dist-info/METADATA
loco-0.1.33.dist-info/WHEEL
loco-0.1.33.dist-info/entry_points.txt
loco-0.1.33.dist-info/top_level.txt
loco-0.1.33.dist-info/RECORD
